flask_tjfu_captcha/__init__.py
flask_tjfu_captcha/flask_tjfu_captcha.py
flask_tjfu_captcha-1.0.0.dist-info/METADATA
flask_tjfu_captcha-1.0.0.dist-info/WHEEL
flask_tjfu_captcha-1.0.0.dist-info/top_level.txt
flask_tjfu_captcha-1.0.0.dist-info/RECORD
