Metadata-Version: 2.1
Name: flask-tjfu-captcha
Version: 1.0.0
Summary: Implement CAPTCHA verification for Flask in a straightforward manner.
Home-page: https://github.com/duynguyen02/flask-tjfu-captcha
Author: duynguyen02
Keywords: Python,Flask
Classifier: Intended Audience :: Developers
Classifier: License :: OSI Approved :: MIT License
Classifier: Programming Language :: Python
Classifier: Operating System :: OS Independent
Requires-Dist: captcha
Requires-Dist: cryptocode
Requires-Dist: Flask
